cryptpandas/SALT.py
cryptpandas/__init__.py
cryptpandas/encrypt_decrypt.py
cryptpandas/tests/__init__.py
cryptpandas/tests/test_IO.py
CryptPandas-1.0.1.dist-info/LICENSE.txt
CryptPandas-1.0.1.dist-info/METADATA
CryptPandas-1.0.1.dist-info/WHEEL
CryptPandas-1.0.1.dist-info/top_level.txt
CryptPandas-1.0.1.dist-info/RECORD
