Metadata-Version: 2.1
Name: CryptPandas
Version: 1.0.1
Summary: A tool for encryption and decryption of pandas dataframes.
Home-page: https://github.com/LucaMingarelli/cryptpandas
Author: Luca Mingarelli
Author-email: lucamingarelli@me.com
License: MIT
Classifier: Programming Language :: Python :: 3
Classifier: License :: OSI Approved :: MIT License
Classifier: Operating System :: OS Independent
Requires-Python: >=3.6
License-File: LICENSE.txt
Requires-Dist: pandas
Requires-Dist: cryptography
Requires-Dist: pyarrow
